{
  "recommendations": [
    {
      "id": 1,
      "name": "4 Queijos",
      "price": "R$ 40,00"
    },
    {
      "id": 2,
      "name": "Gorganzola",
      "price": "R$ 42,00"
    },
    {
      "id": 3,
      "name": "Lombo",
      "price": "R$ 38,00"
    }
  ],
  "pizzas": [
    {
      "id": 1,
      "name": "Calabresa"
    },
    {
      "id": 2,
      "name": "Atum"
    },
    {
      "id": 3,
      "name": "Mussarela"
    },
    {
      "id": 4,
      "name": "4 Queijos"
    },
    {
      "id": 5,
      "name": "2 Queijos"
    },
    {
      "id": 6,
      "name": "Parmesão"
    },
    {
      "id": 7,
      "name": "Escalora"
    },
    {
      "id": 8,
      "name": "Frango c/ Requeijão"
    }
  ],
  "points": [
    10
  ]
}
